seguid_calculator/__init__.py
seguid_calculator/_version.py
seguid_calculator/calculator.py
seguid_calculator/functions.py
seguid_calculator/seguid_flask.py
seguid_calculator-1.27.dist-info/LICENSE.txt
seguid_calculator-1.27.dist-info/METADATA
seguid_calculator-1.27.dist-info/WHEEL
seguid_calculator-1.27.dist-info/entry_points.txt
seguid_calculator-1.27.dist-info/top_level.txt
seguid_calculator-1.27.dist-info/RECORD
