Metadata-Version: 2.1
Name: seguid-calculator
Version: 1.27
Summary: Calculates SEGUID, cSEGUID & lSEGUID checksums for biological sequences
Home-page: https://github.com/BjornFJohansson/seguid_calculator#seguid_calculator
Author: Björn Johansson
Author-email: bjorn_johansson@bio.uminho.pt
License: LICENSE.txt
Keywords: bioinformatics
Classifier: Development Status :: 4 - Beta
Classifier: Environment :: Console
Classifier: Intended Audience :: Education
Classifier: Intended Audience :: Science/Research
Classifier: License :: OSI Approved :: BSD License
Classifier: Programming Language :: Python :: 3.7
Classifier: Programming Language :: Python :: 3.8
Classifier: Programming Language :: Python :: 3.9
Classifier: Programming Language :: Python :: 3.10
Classifier: Programming Language :: Python :: 3.11
Classifier: Topic :: Education
Classifier: Topic :: Scientific/Engineering :: Bio-Informatics
License-File: LICENSE.txt
Requires-Dist: wxpython
